streamlit_arborist/__init__.py
streamlit_arborist/frontend/build/asset-manifest.json
streamlit_arborist/frontend/build/bootstrap.min.css
streamlit_arborist/frontend/build/index.html
streamlit_arborist/frontend/build/static/css/main.c5e7a733.css
streamlit_arborist/frontend/build/static/css/main.c5e7a733.css.map
streamlit_arborist/frontend/build/static/js/main.a679ce71.js
streamlit_arborist/frontend/build/static/js/main.a679ce71.js.LICENSE.txt
streamlit_arborist/frontend/build/static/js/main.a679ce71.js.map
streamlit_arborist/frontend/build/static/media/material-symbols-outlined.55968e9e51644defc4f4.woff2
streamlit_arborist/frontend/build/static/media/material-symbols-rounded.0483b975fd0ac25f323b.woff2
streamlit_arborist/frontend/build/static/media/material-symbols-sharp.818683d6bda01b35ed0e.woff2
streamlit_arborist-0.2.1.dist-info/METADATA
streamlit_arborist-0.2.1.dist-info/WHEEL
streamlit_arborist-0.2.1.dist-info/licenses/LICENSE
streamlit_arborist-0.2.1.dist-info/RECORD
