Metadata-Version: 2.4
Name: streamlit-arborist
Version: 0.2.1
Summary: Streamlit component for creating tree views
Project-URL: homepage, https://github.com/gabriel-msilva/streamlit-arborist
Project-URL: repository, https://github.com/gabriel-msilva/streamlit-arborist
Project-URL: documentation, https://streamlit-arborist.readthedocs.io
Author-email: Gabriel Mello Silva <gabriel.zyx@gmail.com>
License-File: LICENSE
Classifier: Development Status :: 4 - Beta
Classifier: Environment :: Plugins
Classifier: Environment :: Web Environment
Classifier: Intended Audience :: Developers
Classifier: Intended Audience :: Science/Research
Classifier: License :: OSI Approved :: MIT License
Classifier: Programming Language :: Python :: 3.9
Classifier: Programming Language :: Python :: 3.10
Classifier: Programming Language :: Python :: 3.11
Classifier: Programming Language :: Python :: 3.12
Classifier: Programming Language :: Python :: 3.13
Requires-Python: >=3.9
Requires-Dist: streamlit>=1.36.0
